sceodesic/__init__.py
sceodesic/sceo.py
sceodesic/helper/__init__.py
sceodesic/helper/compute_covariance.py
sceodesic/helper/compute_soft_embeddings.py
sceodesic/helper/condition_volume_normalization.py
sceodesic/helper/reassign_clusters.py
sceodesic/sceo_io/__init__.py
sceodesic/sceo_io/sceo_command_line_parser.py
sceodesic/sceo_io/sceo_load_input.py
sceodesic/sceo_main/__init__.py
sceodesic/sceo_main/default_keys.py
sceodesic/sceo_main/estimate_covariances.py
sceodesic/sceo_main/get_cell_cohorts.py
sceodesic/sceo_main/get_locally_variable_genes.py
sceodesic/sceo_main/reconstruct_programs.py
sceodesic/sceo_main/run_sceo.py
sceodesic/sceo_main/write_embedding.py
sceodesic/utils/__init__.py
sceodesic/utils/batch_comps.py
sceodesic/utils/fn_timer.py
sceodesic/utils/order_by_second_moment.py
sceodesic-0.0.5.dist-info/licenses/LICENSE
sceodesic-0.0.5.dist-info/METADATA
sceodesic-0.0.5.dist-info/WHEEL
sceodesic-0.0.5.dist-info/top_level.txt
sceodesic-0.0.5.dist-info/RECORD
