Metadata-Version: 2.4
Name: sceodesic
Version: 0.0.5
Summary: Generate sceodesic embeddings from an input scRNA-seq dataset.
Author-email: Sinan Ozbay <sinan.ozbay@duke.edu>, Aditya Parekh <aditya.parekh@duke.edu>
Project-URL: Homepage, https://github.com/rohitsinghlab/sceodesic
Project-URL: Bug Tracker, https://github.com/rohitsinghlab/sceodesic/issues
Classifier: Programming Language :: Python :: 3
Classifier: License :: OSI Approved :: MIT License
Classifier: Operating System :: OS Independent
License-File: LICENSE
Requires-Dist: setuptools
Requires-Dist: numpy
Requires-Dist: pandas
Requires-Dist: scipy
Requires-Dist: scanpy
Requires-Dist: anndata
Requires-Dist: fbpca
Requires-Dist: scikit-learn
Requires-Dist: PyYaml
Dynamic: license-file
